{"chunk_definitions":[{"row":14,"row_count":1,"visible":true,"expansion_state":0,"options":{"include":false,"engine":"r","label":"setup"},"document_id":"25B91E9D","chunk_id":"csetup_chunk","chunk_label":"setup"},{"row":19,"row_count":1,"visible":true,"expansion_state":0,"options":{"engine":"r","label":"unnamed-chunk-1"},"document_id":"25B91E9D","chunk_id":"cuc946r9b8vzb","chunk_label":"unnamed-chunk-1"},{"row":26,"row_count":1,"visible":true,"expansion_state":0,"options":{"engine":"r","label":"unnamed-chunk-2"},"document_id":"25B91E9D","chunk_id":"c42n51c9734pk","chunk_label":"unnamed-chunk-2"},{"row":62,"row_count":1,"visible":true,"expansion_state":0,"options":{"engine":"r","label":"unnamed-chunk-19"},"document_id":"25B91E9D","chunk_id":"cc6ypuf20vx34","chunk_label":"unnamed-chunk-3"},{"row":88,"row_count":1,"visible":true,"expansion_state":0,"options":{"engine":"r","label":"unnamed-chunk-3"},"document_id":"25B91E9D","chunk_id":"cdf2prr0jkfm5","chunk_label":"unnamed-chunk-4"},{"row":104,"row_count":1,"visible":true,"expansion_state":0,"options":{"engine":"r","label":"unnamed-chunk-4"},"document_id":"25B91E9D","chunk_id":"cemkhr8ypnz6m","chunk_label":"unnamed-chunk-5"},{"row":110,"row_count":1,"visible":true,"expansion_state":0,"options":{"engine":"r","label":"unnamed-chunk-5"},"document_id":"25B91E9D","chunk_id":"c3i8frd9g4a5s","chunk_label":"unnamed-chunk-6"}],"doc_write_time":1672048095,"working_dir":null,"default_chunk_options":{}}